simtrain_eco_mini_app_streamlit_sdk/__init__.py
simtrain_eco_mini_app_streamlit_sdk/sdk.py
simtrain_eco_mini_app_streamlit_sdk/constants/common.py
simtrain_eco_mini_app_streamlit_sdk/services/__init__.py
simtrain_eco_mini_app_streamlit_sdk/services/api_option.py
simtrain_eco_mini_app_streamlit_sdk/services/current.py
simtrain_eco_mini_app_streamlit_sdk/services/helper.py
simtrain_eco_mini_app_streamlit_sdk/services/init_message_bridge.py
simtrain_eco_mini_app_streamlit_sdk/services/ui.py
simtrain_eco_mini_app_streamlit_sdk/services/resources/__init__.py
simtrain_eco_mini_app_streamlit_sdk/services/resources/academy_session.py
simtrain_eco_mini_app_streamlit_sdk/services/resources/account_transaction.py
simtrain_eco_mini_app_streamlit_sdk/services/resources/action_history.py
simtrain_eco_mini_app_streamlit_sdk/services/resources/agent.py
simtrain_eco_mini_app_streamlit_sdk/services/resources/announcement.py
simtrain_eco_mini_app_streamlit_sdk/services/resources/announcement_type.py
simtrain_eco_mini_app_streamlit_sdk/services/resources/app_integration.py
simtrain_eco_mini_app_streamlit_sdk/services/resources/app_integration_log.py
simtrain_eco_mini_app_streamlit_sdk/services/resources/app_message.py
simtrain_eco_mini_app_streamlit_sdk/services/resources/app_user.py
simtrain_eco_mini_app_streamlit_sdk/services/resources/app_user_announcement_view.py
simtrain_eco_mini_app_streamlit_sdk/services/resources/area.py
simtrain_eco_mini_app_streamlit_sdk/services/resources/attendance.py
simtrain_eco_mini_app_streamlit_sdk/services/resources/autoincreament.py
simtrain_eco_mini_app_streamlit_sdk/services/resources/branch.py
simtrain_eco_mini_app_streamlit_sdk/services/resources/category.py
simtrain_eco_mini_app_streamlit_sdk/services/resources/credit_note.py
simtrain_eco_mini_app_streamlit_sdk/services/resources/customfield.py
simtrain_eco_mini_app_streamlit_sdk/services/resources/docnoformat.py
simtrain_eco_mini_app_streamlit_sdk/services/resources/documentevent.py
simtrain_eco_mini_app_streamlit_sdk-0.0.4.dist-info/METADATA
simtrain_eco_mini_app_streamlit_sdk-0.0.4.dist-info/WHEEL
simtrain_eco_mini_app_streamlit_sdk-0.0.4.dist-info/top_level.txt
simtrain_eco_mini_app_streamlit_sdk-0.0.4.dist-info/RECORD
