Metadata-Version: 2.4
Name: simtrain-eco-mini-app-streamlit-sdk
Version: 0.0.4
Summary: SDK for Simtrain Eco Mini App with Streamlit
Author-email: SIMIT GROUP <jhyong@simitgroup.com>
